compteur/__init__.py
compteur/compteur.py
compteur-1.1.dist-info/LICENSE
compteur-1.1.dist-info/METADATA
compteur-1.1.dist-info/WHEEL
compteur-1.1.dist-info/top_level.txt
compteur-1.1.dist-info/RECORD
