Metadata-Version: 2.1
Name: compteur
Version: 1.1
Summary: Count how many time errors occur
Home-page: https://github.com/OlivierProTips/compteur
Author: OlivierProTips
License: MIT
Keywords: Compteur,error,count,track
Classifier: Development Status :: 3 - Alpha
Classifier: Intended Audience :: Developers
Classifier: Topic :: Software Development :: Build Tools
Classifier: License :: OSI Approved :: MIT License
Classifier: Programming Language :: Python :: 3
Classifier: Programming Language :: Python :: 3.4
Classifier: Programming Language :: Python :: 3.5
Classifier: Programming Language :: Python :: 3.6
License-File: LICENSE
